{"assets/fonts/Baloo2-Bold.ttf":["assets/fonts/Baloo2-Bold.ttf"],"assets/fonts/DaveysDoodleface.ttf":["assets/fonts/DaveysDoodleface.ttf"],"assets/images/.DS_Store":["assets/images/.DS_Store"],"assets/images/HappyCloud.png":["assets/images/HappyCloud.png"],"assets/images/HearthEnemy1.png":["assets/images/HearthEnemy1.png"],"assets/images/HearthEnemy2.png":["assets/images/HearthEnemy2.png"],"assets/images/background.png":["assets/images/background.png"],"assets/images/game_logo.png":["assets/images/game_logo.png"],"assets/images/items/.DS_Store":["assets/images/items/.DS_Store"],"assets/images/items/Bubble_Big.png":["assets/images/items/Bubble_Big.png"],"assets/images/items/Bubble_Small.png":["assets/images/items/Bubble_Small.png"],"assets/images/items/Bullet.png":["assets/images/items/Bullet.png"],"assets/images/items/JetFire1.png":["assets/images/items/JetFire1.png"],"assets/images/items/JetFire2.png":["assets/images/items/JetFire2.png"],"assets/images/items/Jetpack_Big.png":["assets/images/items/Jetpack_Big.png"],"assets/images/items/Jetpack_Small.png":["assets/images/items/Jetpack_Small.png"],"assets/images/items/Spring.png":["assets/images/items/Spring.png"],"assets/images/items/bullet_score.png":["assets/images/items/bullet_score.png"],"assets/images/items/coin_score.png":["assets/images/items/coin_score.png"],"assets/images/items/coins.png":["assets/images/items/coins.png"],"assets/images/items/gun.png":["assets/images/items/gun.png"],"assets/images/items/jump_player.png":["assets/images/items/jump_player.png"],"assets/images/items/platform.png":["assets/images/items/platform.png"],"assets/images/items/player.png":["assets/images/items/player.png"],"assets/images/items/thunder.png":["assets/images/items/thunder.png"],"assets/images/items/thunder1.png":["assets/images/items/thunder1.png"],"assets/images/platforms/BrokenLand.png":["assets/images/platforms/BrokenLand.png"],"assets/images/platforms/BrokenLand_left.png":["assets/images/platforms/BrokenLand_left.png"],"assets/images/platforms/BrokenLand_right.png":["assets/images/platforms/BrokenLand_right.png"],"assets/images/platforms/home_platform.png":["assets/images/platforms/home_platform.png"],"assets/images/platforms/platform.png":["assets/images/platforms/platform.png"],"assets/images/platforms/platform2.png":["assets/images/platforms/platform2.png"],"assets/images/platforms/platform3.png":["assets/images/platforms/platform3.png"],"assets/images/platforms/tiles_bg.png":["assets/images/platforms/tiles_bg.png"],"assets/images/platforms/tiles_bg_1.png":["assets/images/platforms/tiles_bg_1.png"],"assets/images/platforms/tree.png":["assets/images/platforms/tree.png"],"assets/images/platforms/tree_bg.png":["assets/images/platforms/tree_bg.png"],"assets/images/ui/buttonBack.png":["assets/images/ui/buttonBack.png"],"assets/images/ui/button_bg.png":["assets/images/ui/button_bg.png"],"assets/images/ui/pause_button.png":["assets/images/ui/pause_button.png"],"assets/images/ui/rope.png":["assets/images/ui/rope.png"],"assets/images/ui/score_bg.png":["assets/images/ui/score_bg.png"],"packages/cupertino_icons/assets/CupertinoIcons.ttf":["packages/cupertino_icons/assets/CupertinoIcons.ttf"]}